kfp_support/api_server_client/README.md
kfp_support/api_server_client/__init__.py
kfp_support/api_server_client/kuberay_apis.py
kfp_support/api_server_client/params/__init__.py
kfp_support/api_server_client/params/cluster.py
kfp_support/api_server_client/params/environmentvariables.py
kfp_support/api_server_client/params/headnode.py
kfp_support/api_server_client/params/jobsubmission.py
kfp_support/api_server_client/params/templates.py
kfp_support/api_server_client/params/volumes.py
kfp_support/api_server_client/params/workernode.py
kfp_support/workflow_support/README.md
kfp_support/workflow_support/utils/__init__.py
kfp_support/workflow_support/utils/components_utils.py
kfp_support/workflow_support/utils/kfp_utils.py
kfp_support/workflow_support/utils/pipeline_utils.py
kfp_support/workflow_support/utils/pipelines_tests_utils.py
kfp_support/workflow_support/utils/remote_jobs_utils.py
data_prep_toolkit_kfp-0.1.1.dist-info/METADATA
data_prep_toolkit_kfp-0.1.1.dist-info/WHEEL
data_prep_toolkit_kfp-0.1.1.dist-info/top_level.txt
data_prep_toolkit_kfp-0.1.1.dist-info/RECORD
