Metadata-Version: 2.1
Name: data_prep_toolkit_kfp
Version: 0.1.1
Summary: Data Preparation Kit Library. KFP support
Author-email: Boris Lublinsky <blublinsky@ibm.com>, Alexey Roytman <roytman@il.ibm.com>, Mohammad Nassar <Mohammad.Nassar@ibm.com>, Revital Eres <eres@il.ibm.com>
License: Apache-2.0
Requires-Python: >=3.10
Requires-Dist: kfp ==1.8.22
Requires-Dist: requests
Requires-Dist: data-prep-toolkit ==0.1.1
Provides-Extra: dev
Requires-Dist: twine ; extra == 'dev'
Requires-Dist: pytest >=7.3.2 ; extra == 'dev'
Requires-Dist: pytest-dotenv >=0.5.2 ; extra == 'dev'
Requires-Dist: pytest-env >=1.0.0 ; extra == 'dev'
Requires-Dist: pre-commit >=3.3.2 ; extra == 'dev'
Requires-Dist: pytest-cov >=4.1.0 ; extra == 'dev'
Requires-Dist: pytest-mock >=3.10.0 ; extra == 'dev'
